xdmod_ondemand_export/__init__.py
xdmod_ondemand_export/conf.ini
xdmod_ondemand_export-1.1.0.dist-info/LICENSE
xdmod_ondemand_export-1.1.0.dist-info/METADATA
xdmod_ondemand_export-1.1.0.dist-info/WHEEL
xdmod_ondemand_export-1.1.0.dist-info/entry_points.txt
xdmod_ondemand_export-1.1.0.dist-info/top_level.txt
xdmod_ondemand_export-1.1.0.dist-info/RECORD
