Metadata-Version: 2.1
Name: xdmod-ondemand-export
Version: 1.1.0
Summary: POST Open OnDemand logs to a web server for inclusion in XDMoD.
Home-page: UNKNOWN
Author: Aaron Weeden
Maintainer: Aaron Weeden, Joseph P. White
License: UNKNOWN
Project-URL: Source Code, https://github.com/ubccr/xdmod-ondemand/tree/main/tools/xdmod-ondemand-export
Platform: UNKNOWN
Requires-Python: >=3.6
License-File: LICENSE
Requires-Dist: apachelogs (>=0.6.0)
Requires-Dist: requests (>=2.27.1)
